clip_inference/__init__.py
clip_inference/dataset.py
clip_inference/load_clip.py
clip_inference/inference/__init__.py
clip_inference/inference/distributor.py
clip_inference/inference/inference.py
clip_inference/inference/logger.py
clip_inference/inference/mapper.py
clip_inference/inference/reader.py
clip_inference/inference/runner.py
clip_inference/inference/worker.py
clip_inference/inference/writer.py
clip_inference-0.0.1.dist-info/LICENSE
clip_inference-0.0.1.dist-info/METADATA
clip_inference-0.0.1.dist-info/WHEEL
clip_inference-0.0.1.dist-info/top_level.txt
clip_inference-0.0.1.dist-info/RECORD
